mmqtt/__init__.py
mmqtt/__main__.py
mmqtt/argument_parser.py
mmqtt/config-example.json
mmqtt/encryption.py
mmqtt/load_config.py
mmqtt/mqtt_client.py
mmqtt/rx_message_handler.py
mmqtt/singleton.py
mmqtt/tx_message_handler.py
mmqtt/utils.py
mmqtt-1.1.3.dist-info/LICENSE
mmqtt-1.1.3.dist-info/METADATA
mmqtt-1.1.3.dist-info/WHEEL
mmqtt-1.1.3.dist-info/entry_points.txt
mmqtt-1.1.3.dist-info/RECORD
